gmsaas/__init__.py
gmsaas/adbtunnel/__init__.py
gmsaas/adbtunnel/adbclient.py
gmsaas/adbtunnel/adbtunnelclient.py
gmsaas/adbtunnel/gmadbtunneld/gmadbtunneld.app/Contents/Info.plist
gmsaas/adbtunnel/gmadbtunneld/gmadbtunneld.app/Contents/Frameworks/libcrypto.1.1.dylib
gmsaas/adbtunnel/gmadbtunneld/gmadbtunneld.app/Contents/Frameworks/libssl.1.1.dylib
gmsaas/adbtunnel/gmadbtunneld/gmadbtunneld.app/Contents/Frameworks/QtConcurrent.framework/QtConcurrent
gmsaas/adbtunnel/gmadbtunneld/gmadbtunneld.app/Contents/Frameworks/QtConcurrent.framework/Resources/Info.plist
gmsaas/adbtunnel/gmadbtunneld/gmadbtunneld.app/Contents/Frameworks/QtConcurrent.framework/Resources/QtConcurrent.prl
gmsaas/adbtunnel/gmadbtunneld/gmadbtunneld.app/Contents/Frameworks/QtConcurrent.framework/Versions/5/QtConcurrent
gmsaas/adbtunnel/gmadbtunneld/gmadbtunneld.app/Contents/Frameworks/QtConcurrent.framework/Versions/5/Resources/Info.plist
gmsaas/adbtunnel/gmadbtunneld/gmadbtunneld.app/Contents/Frameworks/QtConcurrent.framework/Versions/5/Resources/QtConcurrent.prl
gmsaas/adbtunnel/gmadbtunneld/gmadbtunneld.app/Contents/Frameworks/QtConcurrent.framework/Versions/Current/QtConcurrent
gmsaas/adbtunnel/gmadbtunneld/gmadbtunneld.app/Contents/Frameworks/QtConcurrent.framework/Versions/Current/Resources/Info.plist
gmsaas/adbtunnel/gmadbtunneld/gmadbtunneld.app/Contents/Frameworks/QtConcurrent.framework/Versions/Current/Resources/QtConcurrent.prl
gmsaas/adbtunnel/gmadbtunneld/gmadbtunneld.app/Contents/Frameworks/QtCore.framework/QtCore
gmsaas/adbtunnel/gmadbtunneld/gmadbtunneld.app/Contents/Frameworks/QtCore.framework/Resources/Info.plist
gmsaas/adbtunnel/gmadbtunneld/gmadbtunneld.app/Contents/Frameworks/QtCore.framework/Resources/QtCore.prl
gmsaas/adbtunnel/gmadbtunneld/gmadbtunneld.app/Contents/Frameworks/QtCore.framework/Versions/5/QtCore
gmsaas/adbtunnel/gmadbtunneld/gmadbtunneld.app/Contents/Frameworks/QtCore.framework/Versions/5/Resources/Info.plist
gmsaas-1.14.1.dist-info/METADATA
gmsaas-1.14.1.dist-info/WHEEL
gmsaas-1.14.1.dist-info/entry_points.txt
gmsaas-1.14.1.dist-info/top_level.txt
gmsaas-1.14.1.dist-info/RECORD
