Metadata-Version: 2.1
Name: gmsaas
Version: 1.14.1
Summary: Universal Command Line Interface for Genymotion Cloud SaaS
Home-page: https://cloud.geny.io
Author: Genymobile
Author-email: contact@genymobile.com
License: Proprietary
Platform: any
Classifier: Development Status :: 5 - Production/Stable
Classifier: Environment :: Console
Classifier: Intended Audience :: Developers
Classifier: License :: Other/Proprietary License
Classifier: Operating System :: MacOS :: MacOS X
Classifier: Operating System :: POSIX :: Linux
Classifier: Operating System :: Microsoft :: Windows
Classifier: Programming Language :: Python
Classifier: Programming Language :: Python :: 3
Classifier: Topic :: Software Development :: Quality Assurance
Classifier: Topic :: Software Development :: Testing
Classifier: Topic :: Software Development :: Embedded Systems
Classifier: Topic :: System :: Emulators
Requires-Python: >=3.8
Requires-Dist: click
Requires-Dist: PySocks
Requires-Dist: requests
Requires-Dist: requests-toolbelt
Requires-Dist: tabulate
Requires-Dist: python-engineio
Requires-Dist: python-socketio>=5
Requires-Dist: websocket-client
Requires-Dist: psutil
Requires-Dist: pyperclip
Requires-Dist: packaging
Requires-Dist: importlib-resources; python_version < "3.9"
